ogdc_runner/__init__.py
ogdc_runner/__main__.py
ogdc_runner/_version.py
ogdc_runner/_version.pyi
ogdc_runner/api.py
ogdc_runner/argo.py
ogdc_runner/constants.py
ogdc_runner/exceptions.py
ogdc_runner/inputs.py
ogdc_runner/publish.py
ogdc_runner/py.typed
ogdc_runner/models/__init__.py
ogdc_runner/models/recipe_config.py
ogdc_runner/recipe/__init__.py
ogdc_runner/recipe/shell.py
ogdc_runner/recipe/viz_workflow.py
ogdc_runner-0.1.0.dist-info/METADATA
ogdc_runner-0.1.0.dist-info/WHEEL
ogdc_runner-0.1.0.dist-info/entry_points.txt
ogdc_runner-0.1.0.dist-info/licenses/LICENSE
ogdc_runner-0.1.0.dist-info/RECORD
