Metadata-Version: 2.4
Name: ogdc-runner
Version: 0.1.0
Summary: Defines OGDC recipe API(s) and submits recipes to OGDC for execution
Project-URL: Homepage, https://github.com/qgreenland-net/ogdc-runner
Project-URL: Bug Tracker, https://github.com/qgreenland-net/ogdc-runner/issues
Project-URL: Discussions, https://github.com/qgreenland-net/ogdc-runner/discussions
Project-URL: Changelog, https://github.com/qgreenland-net/ogdc-runner/releases
Author-email: Matt Fisher <mfisher87@gmail.com>, Rushiraj Nenuji <nenuji@nceas.ucsb.edu>, Trey Stafford <trey.stafford@colorado.edu>, Robyn Marowitz <robyn.marowitz@colorado.edu>
License: Copyright 2024 National Snow and Ice Data Center & Regents of the University of California
License-File: LICENSE
Classifier: Development Status :: 1 - Planning
Classifier: Intended Audience :: Developers
Classifier: Intended Audience :: Science/Research
Classifier: License :: OSI Approved :: MIT License
Classifier: Operating System :: OS Independent
Classifier: Programming Language :: Python
Classifier: Programming Language :: Python :: 3
Classifier: Programming Language :: Python :: 3 :: Only
Classifier: Programming Language :: Python :: 3.11
Classifier: Programming Language :: Python :: 3.12
Classifier: Topic :: Scientific/Engineering
Classifier: Typing :: Typed
Requires-Python: >=3.11
Requires-Dist: click>=8
Requires-Dist: fsspec
Requires-Dist: hera>=5.18.0
Requires-Dist: loguru
Requires-Dist: pydantic>=2.7.1
Requires-Dist: pyyaml
Provides-Extra: dev
Requires-Dist: mypy~=1.10.0; extra == 'dev'
Requires-Dist: nox; extra == 'dev'
Requires-Dist: pytest-cov>=3; extra == 'dev'
Requires-Dist: pytest>=6; extra == 'dev'
Requires-Dist: types-pyyaml; extra == 'dev'
Provides-Extra: docs
Requires-Dist: autodoc-pydantic; extra == 'docs'
Requires-Dist: furo>=2023.08.17; extra == 'docs'
Requires-Dist: myst-parser>=0.13; extra == 'docs'
Requires-Dist: sphinx-autodoc-typehints; extra == 'docs'
Requires-Dist: sphinx-copybutton; extra == 'docs'
Requires-Dist: sphinx>=7.0; extra == 'docs'
Requires-Dist: sphinxcontrib-mermaid; extra == 'docs'
Provides-Extra: test
Requires-Dist: mypy~=1.10.0; extra == 'test'
Requires-Dist: pytest-cov>=3; extra == 'test'
Requires-Dist: pytest-order; extra == 'test'
Requires-Dist: pytest>=6; extra == 'test'
Requires-Dist: types-pyyaml; extra == 'test'
